sniffer/__init__.py
sniffer/api.py
sniffer/broadcasters.py
sniffer/main.py
sniffer/metadata.py
sniffer/modules_restore_point.py
sniffer/runner.py
sniffer/scent_picker.py
sniffer/scanner/__init__.py
sniffer/scanner/base.py
sniffer/scanner/fsevents_scanner.py
sniffer/scanner/pyinotify_scanner.py
sniffer/scanner/pywin_scanner.py
sniffer/tests/__init__.py
sniffer/tests/scent_file.py
sniffer/tests/test_api.py
sniffer/tests/test_scent_module.py
sniffer-0.4.1.dist-info/LICENSE.txt
sniffer-0.4.1.dist-info/METADATA
sniffer-0.4.1.dist-info/WHEEL
sniffer-0.4.1.dist-info/entry_points.txt
sniffer-0.4.1.dist-info/top_level.txt
sniffer-0.4.1.dist-info/RECORD
