Metadata-Version: 2.1
Name: sniffer
Version: 0.4.1
Summary: An automatic test runner. Supports nose out of the box.
Home-page: http://github.com/jeffh/sniffer/
Author: Jeff Hui
Author-email: jeff@jeffhui.net
License: MIT
Platform: UNKNOWN
Classifier: Development Status :: 3 - Alpha
Classifier: Environment :: Console
Classifier: Intended Audience :: Developers
Classifier: License :: OSI Approved :: MIT License
Classifier: Operating System :: OS Independent
Classifier: Programming Language :: Python
Classifier: Programming Language :: Python :: 3
Classifier: Topic :: Software Development :: Testing
Provides-Extra: Growl
Provides-Extra: LibNotify
Provides-Extra: Linux
Provides-Extra: OSX
